volcengine/bootstrap/__init__.py
volcengine/bootstrap/bootstrap.py
volcengine/bootstrap/bootstrap_gen.py
volcengine/bootstrap/envs.py
volcengine/bootstrap/utils.py
volcengine/bootstrap/version.py
volcengine_tls_bootstrap-1.0.2.dist-info/METADATA
volcengine_tls_bootstrap-1.0.2.dist-info/WHEEL
volcengine_tls_bootstrap-1.0.2.dist-info/entry_points.txt
volcengine_tls_bootstrap-1.0.2.dist-info/RECORD
